uts/__init__.py
uts/authentication.py
uts/httpHandler.py
uts/utils.py
uts/uts.py
ultratimeseries_api-1.0.6.dist-info/METADATA
ultratimeseries_api-1.0.6.dist-info/WHEEL
ultratimeseries_api-1.0.6.dist-info/license.md
ultratimeseries_api-1.0.6.dist-info/top_level.txt
ultratimeseries_api-1.0.6.dist-info/RECORD
