Metadata-Version: 2.1
Name: ultratimeseries-api
Version: 1.0.6
Summary: A python wrapper around the UTS REST API.
Home-page: UNKNOWN
Author: Two Impulse
Author-email: daniel.mendonca@twoimpulse.com
License: Apache Software License (http://www.apache.org/licenses/LICENSE-2.0)
Platform: UNKNOWN
Classifier: License :: OSI Approved :: Apache Software License
Classifier: Programming Language :: Python :: 3
Classifier: Programming Language :: Python :: 3.6
Requires-Dist: requests
